{
  "title": "Price",
  "items": [
    {
      "heading": "30 Day Trial",
      "currentClass": "current",
      "image": {
        "url": "../../../dist/img/trial.svg"
      },
      "introText": "An Ugly Myspace Profile Will Sure Ruin Your Reputation",
      "price": "Free",
      "priceText": "Guidelines For Inkjet Cartridge Refill",
      "benefits": [
        {
          "item": "Members <strong>Free</strong>"
        },
        {
          "item": "Project <strong>1</strong>"
        },
        {
          "item": "User <strong>1</strong>"
        }
      ]
    },
    {
      "heading": "Personal",
      "currentClass": "",
      "image": {
        "url": "../../../dist/img/pers1.svg"
      },
      "introText": "An Ugly Myspace Profile Will Sure Ruin Your Reputation",
      "price": "19",
      "priceText": "Guidelines For Inkjet Cartridge Refill",
      "benefits": [
        {
          "item": "Members <strong>Free</strong>"
        },
        {
          "item": "Project <strong>5</strong>"
        },
        {
          "item": "User <strong>5</strong>"
        }
      ]
    },
    {
      "heading": "Personal",
      "currentClass": "",
      "image": {
        "url": "../../../dist/img/pers2.svg"
      },
      "introText": "An Ugly Myspace Profile Will Sure Ruin Your Reputation",
      "price": "19",
      "priceText": "Guidelines For Inkjet Cartridge Refill",
      "benefits": [
        {
          "item": "Members <strong>Free</strong>"
        },
        {
          "item": "Project <strong>5</strong>"
        },
        {
          "item": "User <strong>5</strong>"
        }
      ]
    },
    {
      "heading": "Advanced",
      "currentClass": "",
      "image": {
        "url": "../../../dist/img/advanced.svg"
      },
      "introText": "An Ugly Myspace Profile Will Sure Ruin Your Reputation",
      "price": "49",
      "priceText": "Guidelines For Inkjet Cartridge Refill",
      "benefits": [
        {
          "item": "Members <strong>Free</strong>"
        },
        {
          "item": "Project <strong>30</strong>"
        },
        {
          "item": "User <strong>Unlimited</strong>"
        },
        {
          "item": "Storage <strong>20Gb</strong>"
        },
        {
          "item": "More <strong>Unmatched Toner Cartridge Quality 20</strong>"
        }
      ]
    }
  ]
}